torchcontrol/__init__.py
torchcontrol/controllers/__init__.py
torchcontrol/controllers/controller_base.py
torchcontrol/controllers/controller_cfg.py
torchcontrol/controllers/mppi.py
torchcontrol/controllers/mppi_cfg.py
torchcontrol/controllers/pid.py
torchcontrol/controllers/pid_cfg.py
torchcontrol/observers/__init__.py
torchcontrol/observers/observer_base.py
torchcontrol/observers/observer_cfg.py
torchcontrol/plants/__init__.py
torchcontrol/plants/input_output_system.py
torchcontrol/plants/input_output_system_cfg.py
torchcontrol/plants/nonlinear_system.py
torchcontrol/plants/nonlinear_system_cfg.py
torchcontrol/plants/plant_base.py
torchcontrol/plants/plant_cfg.py
torchcontrol/plants/state_space_system.py
torchcontrol/plants/state_space_system_cfg.py
torchcontrol/system/__init__.py
torchcontrol/system/parameters.py
torchcontrol/system/system_base.py
torchcontrol/system/system_cfg.py
torchcontrol/utils/__init__.py
torchcontrol/utils/math.py
torchcontrol/utils/visualization.py
torchcontrol-0.1.5.dist-info/licenses/LICENSE
torchcontrol-0.1.5.dist-info/METADATA
torchcontrol-0.1.5.dist-info/WHEEL
torchcontrol-0.1.5.dist-info/top_level.txt
torchcontrol-0.1.5.dist-info/RECORD
