Metadata-Version: 2.4
Name: torchcontrol
Version: 0.1.5
Summary: A parallel control system simulation and control library based on PyTorch.
Author: Tang Longbin
Requires-Python: >=3.8
License-File: LICENSE
Requires-Dist: torch
Requires-Dist: torchdiffeq
Requires-Dist: scipy
Requires-Dist: numpy
Requires-Dist: matplotlib
Requires-Dist: tqdm
Requires-Dist: imageio
Dynamic: license-file
Dynamic: requires-python
